.coveragerc
.flake8
.gitignore
.gitlab-ci.yml
CITATION.cff
CONTRIBUTING.md
Dockerfile
Dockerfile.scheduled
LICENSE
MANIFEST.in
README.rst
pyproject.toml
setup.py
calorine/__init__.py
calorine.egg-info/PKG-INFO
calorine.egg-info/SOURCES.txt
calorine.egg-info/dependency_links.txt
calorine.egg-info/requires.txt
calorine.egg-info/top_level.txt
calorine/calculators/__init__.py
calorine/calculators/cpunep.py
calorine/calculators/gpunep.py
calorine/gpumd/__init__.py
calorine/gpumd/io.py
calorine/nep/__init__.py
calorine/nep/io.py
calorine/nep/model.py
calorine/nep/nep.py
calorine/nep/training_factory.py
calorine/tools/__init__.py
calorine/tools/analysis.py
calorine/tools/entropy.py
calorine/tools/phonons.py
calorine/tools/stiffness.py
calorine/tools/structures.py
doc/conf.py
doc/credits.rst
doc/genindex.rst
doc/index.rst
doc/_static/custom.css
doc/_static/delete_empty_code_blocks.js
doc/_static/hidden_cells.css
doc/_static/hidden_cells.js
doc/_static/logo.ico
doc/_static/logo.png
doc/_static/model-analysis.png
doc/_static/parity-plot.png
doc/_static/phase-diagram.png
doc/_static/phonon-dispersion.png
doc/_static/switcher.json
doc/_templates/breadcrumbs.html
doc/_templates/page.html
doc/get_started/calculators.ipynb
doc/get_started/elastic_stiffness_tensor.ipynb
doc/get_started/faq.rst
doc/get_started/free_energy_tutorial.ipynb
doc/get_started/generate_training_structures_and_training.ipynb
doc/get_started/index.rst
doc/get_started/installation.rst
doc/get_started/nep_descriptors.ipynb
doc/get_started/nep_model_inspection.ipynb
doc/get_started/phonons.ipynb
doc/get_started/simulating_ins.ipynb
doc/get_started/structure_relaxation.ipynb
doc/get_started/thermal_conductivity_from_bte.ipynb
doc/get_started/visualize_descriptor_space_with_pca.ipynb
doc/reference/calculators.rst
doc/reference/gpumd.rst
doc/reference/index.rst
doc/reference/nep.rst
doc/reference/tools.rst
src/nepy/README.md
src/nepy/dftd3para.h
src/nepy/ewald.cpp
src/nepy/ewald.h
src/nepy/neighbor.cpp
src/nepy/neighbor.h
src/nepy/nep.cpp
src/nepy/nep.h
src/nepy/nep_utilities.h
src/nepy/nepy.cpp
src/nepy/nepy.h
tutorials/CsPbI3-cubic-Pm-3m.xyz
