Metadata-Version: 2.1
Name: calorine
Version: 3.3
Summary: A Python library for building and sampling NEP models via the GPUMD package
Author: The calorine developers team
Maintainer: The calorine developers team
License: Mozilla Public License Version 2.0
Project-URL: Documentation, https://calorine.materialsmodeling.org
Project-URL: Repository, https://gitlab.com/materials-modeling/calorine/
Keywords: chemistry,physics,scientific
Classifier: Development Status :: 5 - Production/Stable
Classifier: Operating System :: OS Independent
Classifier: Programming Language :: Python :: 3 :: Only
Classifier: Programming Language :: Python :: 3
Classifier: Programming Language :: Python :: 3.8
Classifier: Programming Language :: Python :: 3.9
Classifier: Programming Language :: Python :: 3.10
Classifier: Programming Language :: Python :: 3.11
Classifier: Intended Audience :: Science/Research
Classifier: Topic :: Scientific/Engineering :: Physics
Requires-Python: >=3.8
Provides-Extra: additional_features
Provides-Extra: documentation
Provides-Extra: test
License-File: LICENSE
